bckt/permissions.py
bckt/models.py
bckt/__init__.py
bckt/views.py
bckt/admin.py
bckt/serializers.py
pyreststore/settings.py
pyreststore/urls.py
pyreststore/__init__.py
pyreststore/settings_local.py
pyreststore/settings_dev.py
pyreststore/wsgi.py
pyreststore-0.9.0.dist-info/DESCRIPTION.rst
pyreststore-0.9.0.dist-info/RECORD
pyreststore-0.9.0.dist-info/WHEEL
pyreststore-0.9.0.dist-info/top_level.txt
pyreststore-0.9.0.dist-info/METADATA
pyreststore-0.9.0.dist-info/metadata.json
