Metadata-Version: 2.0
Name: pyreststore
Version: 0.9.0
Summary: Python implementation of a REST based storage
Home-page: https://github.com/peterdv/pyreststore
Author: Peter Dahl Vestergaard
Author-email: peter.dahl.vestergaard@gmail.com
License: BSD 3-Clause
Keywords: REST
Platform: UNKNOWN
Requires-Dist: django
Requires-Dist: django-filter
Requires-Dist: djangorestframework
Requires-Dist: djangorestframework-jwt
Requires-Dist: django-rest-swagger
Requires-Dist: django-filter
